MANIFEST.in
setup.cfg
setup.py
goulash/__init__.py
goulash/_fabric.py
goulash/_inspect.py
goulash/_os.py
goulash/allstatic.py
goulash/ansi.py
goulash/boiler.py
goulash/cache.py
goulash/decorators.py
goulash/docs.py
goulash/fileserver.py
goulash/heuristics.py
goulash/metaclasses.py
goulash/namespaces.py
goulash/net.py
goulash/parsing.py
goulash/projects.py
goulash/python.py
goulash/reflect.py
goulash/set.py
goulash/settings.py
goulash/stdout.py
goulash/util.py
goulash/venv.py
goulash/version.py
goulash/wrappers.py
goulash.egg-info/PKG-INFO
goulash.egg-info/SOURCES.txt
goulash.egg-info/dependency_links.txt
goulash.egg-info/entry_points.txt
goulash.egg-info/pbr.json
goulash.egg-info/requires.txt
goulash.egg-info/top_level.txt
goulash/bin/__init__.py
goulash/bin/_goulash.py
goulash/data/__init__.py
goulash/data/docs_requirements.txt
goulash/data/epydoc.css
goulash/data/mkdocs.yml
goulash/data/setup.py
goulash/data/tox.ini
goulash/data/glsh/base.html
goulash/data/glsh/content.html
goulash/data/glsh/nav.html
goulash/data/glsh/toc.html
goulash/data/glsh/css/base.css
goulash/data/glsh/css/bootstrap-custom.min.css
goulash/data/glsh/css/font-awesome-4.0.3.css
goulash/data/glsh/css/highlight.css
goulash/data/glsh/fonts/fontawesome-webfont.eot
goulash/data/glsh/fonts/fontawesome-webfont.svg
goulash/data/glsh/fonts/fontawesome-webfont.ttf
goulash/data/glsh/fonts/fontawesome-webfont.woff
goulash/data/glsh/img/favicon.ico
goulash/data/glsh/js/base.js
goulash/data/glsh/js/bootstrap-3.0.3.min.js
goulash/data/glsh/js/highlight.pack.js
goulash/data/glsh/js/jquery-1.10.2.min.js
goulash/data/pkg/__init__.py
goulash/data/pkg/util.py
goulash/data/pkg/version.py