Metadata-Version: 1.1
Name: goulash
Version: 0.67
Summary: toolbox, random shared stuff from my other projects
Home-page: https://github.com/mattvonrocketstein/goulash/
Author: mattvonrocketstein
Author-email: $author@gmail
License: UNKNOWN
Download-URL: https://github.com/mattvonrocketstein/goulash//tarball/master
Keywords: goulash
Platform: UNKNOWN
